Workbook

Sheet Reconstructed P&L
A1: NTPC Ltd. – Reconstructed Profit & Loss Account
A2: ₹ Crore | FY 2015-16 to FY 2024-25
A4: Particulars | B4: Mar 2016 | C4: Mar 2017 | D4: Mar 2018 | E4: Mar 2019 | F4: Mar 2020 | G4: Mar 2021 | H4: Mar 2022 | I4: Mar 2023 | J4: Mar 2024 | K4: Mar 2025
A5: Sales / Revenue (Revenue from Operations) | B5: 70843.81 | C5: 78537.36 | D5: 86713.55 | E5: 86466.09 | F5: 102529.23 | G5: 100986.11 | H5: 122588.98 | I5: 163178.68 | J5: 163143.2 | K5: 173350.07
A6: (-) Cost of Goods Sold / Direct Cost | B6: =43798.59+0+0 -> 43798.59 | C6: =47572.19+0+0 -> 47572.19 | D6: =48315.47+1313.51+0 -> 49628.98 | E6: =52493.74+2713.68+0 -> 55207.42 | F6: =54241.82+2776.44+0 -> 57018.26 | G6: =52849.64+3031.25+0 -> 55880.89 | H6: =66570.07+3450.22+0 -> 70020.29 | I6: =96851.5+3656.26+0 -> 100507.76 | J6: =94037.49+3881.66+0 -> 97919.15 | K6: =97060.24+3767.7+0 -> 100827.94
A7: Gross Profit | B7: =B5-B6 -> 27045.22 | C7: =C5-C6 -> 30965.17 | D7: =D5-D6 -> 37084.57 | E7: =E5-E6 -> 31258.67 | F7: =F5-F6 -> 45510.97 | G7: =G5-G6 -> 45105.22 | H7: =H5-H6 -> 52568.69 | I7: =I5-I6 -> 62670.92 | ... K7: =K5-K6 -> 72522.13
A8: (-) Operating Expenses (incl. Depreciation) | B8: =3581.65+5172.34+5564.4 -> 14318.39 | C8: =4324.6+5920.82+5092.38 -> 15337.8 | D8: =4734.67+7098.86+7421.73 -> 19255.26 | E8: =4779.89+7254.36+7548.63 -> 19582.88 | F8: =4925.6+8622.85+8663.81 -> 22212.26 | G8: =4942.19+10411.8+9580.28 -> 24934.27 | H8: =5412.07+12058.24+9717.19 -> 27187.5 | I8: =5559.03+13136.71+14474.59 -> 33170.33 | J8: =5670.1+13943.15+15213.43 -> 34826.68 | K8: =5724.67+15055.84+18111.6 -> 38892.11
A9: Operating Profit (EBIT) | B9: =B7-B8 -> 12726.83 | C9: =C7-C8 -> 15627.37 | D9: =D7-D8 -> 17829.31 | E9: =E7-E8 -> 11675.79 | F9: =F7-F8 -> 23298.71 | G9: =G7-G8 -> 20170.95 | H9: =H7-H8 -> 25381.19 | I9: =I7-I8 -> 29500.59 | ... K9: =K7-K8 -> 33630.02
A10: (+) Other / Non-operating Income | B10: 1165.35 | C10: 1068.86 | D10: 1755.25 | E10: 1872.13 | F10: 2778.02 | G10: 4345.99 | H10: 3575.11 | I10: 3954.64 | J10: 3698.32 | K10: 4376.12
A11: (+/-) Exceptional Items | B11: 0 | C11: -782.95 | D11: 0 | E11: 0 | F11: 0 | G11: -1363 | H11: 0 | I11: 0 | J11: 834.55 | K11: 0
A12: EBIT after adjustments | B12: =B9+B10+B11 -> 13892.18 | C12: =C9+C10+C11 -> 15913.28 | D12: =D9+D10+D11 -> 19584.56 | E12: =E9+E10+E11 -> 13547.92 | F12: =F9+F10+F11 -> 26076.73 | G12: =G9+G10+G11 -> 23153.94 | H12: =H9+H10+H11 -> 28956.3 | I12: =I9+I10+I11 -> 33455.23 | ... K12: =K9+K10+K11 -> 38006.14
A13: (-) Interest / Finance Cost | B13: 3296.41 | C13: 3597.2 | D13: 3984.25 | E13: 4716.74 | F13: 6781.97 | G13: 7459.03 | H13: 8216.54 | I13: 9979.23 | J13: 10250.82 | K13: 11057.04
A14: Earnings Before Tax (EBT) | B14: =B12-B13 -> 10595.77 | C14: =C12-C13 -> 12316.08 | D14: =D12-D13 -> 15600.31 | E14: =E12-E13 -> 8831.18 | F14: =F12-F13 -> 19294.76 | G14: =G12-G13 -> 15694.91 | H14: =H12-H13 -> 20739.76 | I14: =I12-I13 -> 23476 | ... K14: =K12-K13 -> 26949.1
A15: (-) Tax Expense | B15: -173.83 | C15: 2930.82 | D15: 5257.14 | E15: -2918.71 | F15: 9181.95 | G15: 1925.39 | H15: 4457.77 | I15: 6279.27 | J15: 6600.03 | K15: 7299.69
A16: Net Profit | B16: =B14-B15 -> 10769.6 | C16: =C14-C15 -> 9385.26 | D16: =D14-D15 -> 10343.17 | E16: =E14-E15 -> 11749.89 | F16: =F14-F15 -> 10112.81 | G16: =G14-G15 -> 13769.52 | H16: =H14-H15 -> 16281.99 | I16: =I14-I15 -> 17196.73 | ... K16: =K14-K15 -> 19649.41

Sheet P & L
A1: Particulars | B1: Mar 2016 | C1: Mar 2017 | D1: Mar 2018 | E1: Mar 2019 | F1: Mar 2020 | G1: Mar 2021 | H1: Mar 2022 | I1: Mar 2023 | J1: Mar 2024 | K1: Mar 2025
A2: - | B2: 0 | C2: 0 | D2: 0 | E2: 0 | F2: 0 | G2: 0 | H2: 0 | I2: 0 | J2: 0 | K2: 0
A3: Total Income | B3: 72009.16 | C3: 79606.22 | D3: 88468.8 | E3: 88338.22 | F3: 105307.25 | G3: 105332.1 | H3: 126164.09 | I3: 167133.32 | J3: 166841.52 | K3: 177726.19
A4: Revenue From Operations(Net) | B4: 70843.81 | C4: 78537.36 | D4: 86713.55 | E4: 86466.09 | F4: 102529.23 | G4: 100986.11 | H4: 122588.98 | I4: 163178.68 | J4: 163143.2 | K4: 173350.07
A5: Revenue From Sale of Products | B5: 70301.91 | C5: 77739.16 | D5: 84789.94 | E5: 85923.89 | F5: 102272.17 | G5: 100571.65 | H5: 122401.21 | I5: 163024.6 | J5: 162972.61 | K5: 173183.6
A6: Revenue From Sale of Services | B6: 0 | C6: 0 | D6: 0 | E6: 0 | F6: 0 | G6: 247.37 | H6: 187.77 | I6: 154.08 | J6: 170.59 | K6: 166.47
A7: Other operating Revenue | B7: 541.9 | C7: 798.2 | D7: 1923.61 | E7: 542.2 | F7: 257.06 | G7: 167.09 | H7: 0 | I7: 0 | J7: 0 | K7: 0
A8: Less:Indirect Taxes | B8: 0 | C8: 0 | D8: 0 | E8: 0 | F8: 0 | G8: 0 | H8: 0 | I8: 0 | J8: 0 | K8: 0
A9: Revenue from Interest | B9: 0 | C9: 0 | D9: 0 | E9: 0 | F9: 0 | G9: 0 | H9: 0 | I9: 0 | J9: 0 | K9: 0
A10: Revenue from Other Financial Services | B10: 0 | C10: 0 | D10: 0 | E10: 0 | F10: 0 | G10: 0 | H10: 0 | I10: 0 | J10: 0 | K10: 0
A11: Other Income | B11: 1165.35 | C11: 1068.86 | D11: 1755.25 | E11: 1872.13 | F11: 2778.02 | G11: 4345.99 | H11: 3575.11 | I11: 3954.64 | J11: 3698.32 | K11: 4376.12
A12: Total Expenses | B12: 61413.39 | C12: 66507.19 | D12: 72868.49 | E12: 79507.04 | F12: 86012.49 | G12: 88274.19 | H12: 105424.33 | I12: 143657.32 | J12: 142996.65 | K12: 150777.09
A13: Cost of material consumed | B13: 43798.59 | C13: 47572.19 | D13: 48315.47 | E13: 52493.74 | F13: 54241.82 | G13: 52849.64 | H13: 66570.07 | I13: 96851.5 | J13: 94037.49 | K13: 97060.24
... A34: Diluted earnings per equity share | B34: 13.06 | C34: 11.38 | D34: 10.45 | E34: 11.88 | F34: 10.22 | G34: 13.99 | H34: 15.33 | I34: 0 | J34: 18.64 | K34: 20.26

Sheet  Balance Sheet
A1: Particulars | B1: Mar 2016 | C1: Mar 2017 | D1: Mar 2018 | E1: Mar 2019 | F1: Mar 2020 | G1: Mar 2021 | H1: Mar 2022 | I1: Mar 2023 | J1: Mar 2024 | K1: Mar 2025
A2: - | B2: 0 | C2: 0 | D2: 0 | E2: 0 | F2: 0 | G2: 0 | H2: 0 | I2: 0 | J2: 0 | K2: 0
A3: Equity & Liabilities | B3: 215138.32 | C3: 236577.49 | D3: 267832.09 | E3: 290750.96 | F3: 327667.45 | G3: 343176.92 | H3: 371140.44 | I3: 383674.45 | J3: 393294.53 | K3: 407917.66
A4: Equity | B4: 91293.7 | C4: 96231.23 | D4: 101777.77 | E4: 107408.17 | F4: 113569.44 | G4: 118985.49 | H4: 128667.52 | I4: 138889.88 | J4: 149885.02 | K4: 161640.55
A5: Share Capital | B5: 8245.46 | C5: 8245.46 | D5: 8245.46 | E5: 9894.56 | F5: 9894.56 | G5: 9696.67 | H5: 9696.67 | I5: 9696.67 | J5: 9696.67 | K5: 9696.67
A6: Reserves & Surplus | B6: 83048.24 | C6: 87985.77 | D6: 93532.31 | E6: 97513.61 | F6: 103674.88 | G6: 109288.82 | H6: 118970.85 | I6: 129193.21 | J6: 140188.35 | K6: 151943.88
A7: Money received against share warrants | B7: 0 | C7: 0 | D7: 0 | E7: 0 | F7: 0 | G7: 0 | H7: 0 | I7: 0 | J7: 0 | K7: 0
A8: Non-Current liabilities | B8: 92085.88 | C8: 104168.94 | D8: 123499.56 | E8: 127988.79 | F8: 159393.85 | G8: 166141.72 | H8: 174549.81 | I8: 170049.43 | J8: 162777.34 | K8: 164575.65
A9: Long term Borrowings | B9: 85096.95 | C9: 97339.28 | D9: 108697.6 | E9: 119698.08 | F9: 146538.7 | G9: 151229.62 | H9: 160122.17 | I9: 156315.69 | J9: 146159.07 | K9: 144365.56
A10: Long term Provisions | B10: 436.41 | C10: 463.15 | D10: 480.9 | E10: 588.74 | F10: 826.74 | G10: 1174.21 | H10: 1446.48 | I10: 1727.78 | J10: 1898.03 | K10: 1937.69
A11: Net Deferred Tax Liabilities | B11: 1152.21 | C11: 1484.84 | D11: 10047.16 | E11: 4200.14 | F11: 8093.98 | G11: 9160.99 | H11: 10184.39 | I11: 10614.07 | J11: 13066.53 | K11: 16527.06
A12: Other Long Term Liabilities | B12: 5400.31 | C12: 4881.67 | D12: 4273.9 | E12: 3501.83 | F12: 3934.43 | G12: 4576.9 | H12: 2796.77 | I12: 1391.89 | J12: 1653.71 | K12: 1745.34
A13: Current liabilities | B13: 31758.74 | C13: 36177.32 | D13: 42554.76 | E13: 55354 | F13: 54704.16 | G13: 58049.71 | H13: 67923.11 | I13: 74735.14 | J13: 80632.17 | K13: 81701.46
... A40: Total contingent liabilities and commitments | B40: 19257.68 | C40: 86543.18 | D40: 86684.66 | E40: 93382.31 | F40: 112243.24 | G40: 43066.09 | H40: 33980.49 | I40: 24169.45 | J40: 24046.64 | K40: 23284

Sheet Financial Ratios
A1: NTPC Ltd. – Financial Ratio Analysis
A2: Only ratios shown in the attached notes that can reasonably be calculated from the supplied statements are included.
A4: Ratio | B4: Mar 2016 | C4: Mar 2017 | D4: Mar 2018 | E4: Mar 2019 | F4: Mar 2020 | G4: Mar 2021 | H4: Mar 2022 | I4: Mar 2023 | J4: Mar 2024 | K4: Mar 2025
A5: 1. PROFITABILITY RATIOS
A6: Gross Profit Margin (%) | B6: ='Reconstructed P&L'!B7/'Reconstructed P&L'!B5*100 -> 38.175841 | C6: ='Reconstructed P&L'!C7/'Reconstructed P&L'!C5*100 -> 39.427312 | D6: ='Reconstructed P&L'!D7/'Reconstructed P&L'!D5*100 -> 42.766753 | E6: ='Reconstructed P&L'!E7/'Reconstructed P&L'!E5*100 -> 36.151363 | F6: ='Reconstructed P&L'!F7/'Reconstructed P&L'!F5*100 -> 44.388288 | G6: ='Reconstructed P&L'!G7/'Reconstructed P&L'!G5*100 -> 44.664776 | H6: ='Reconstructed P&L'!H7/'Reconstructed P&L'!H5*100 -> 42.882068 | I6: ='Reconstructed P&L'!I7/'Reconstructed P&L'!I5*100 -> 38.406316 | ... K6: ='Reconstructed P&L'!K7/'Reconstructed P&L'!K5*100 -> 41.835651
A7: Operating Profit Margin (%) | B7: ='Reconstructed P&L'!B9/'Reconstructed P&L'!B5*100 -> 17.964632 | C7: ='Reconstructed P&L'!C9/'Reconstructed P&L'!C5*100 -> 19.898008 | D7: ='Reconstructed P&L'!D9/'Reconstructed P&L'!D5*100 -> 20.561158 | E7: ='Reconstructed P&L'!E9/'Reconstructed P&L'!E5*100 -> 13.503317 | F7: ='Reconstructed P&L'!F9/'Reconstructed P&L'!F5*100 -> 22.723969 | G7: ='Reconstructed P&L'!G9/'Reconstructed P&L'!G5*100 -> 19.973985 | H7: ='Reconstructed P&L'!H9/'Reconstructed P&L'!H5*100 -> 20.7043 | I7: ='Reconstructed P&L'!I9/'Reconstructed P&L'!I5*100 -> 18.078704 | ... K7: ='Reconstructed P&L'!K9/'Reconstructed P&L'!K5*100 -> 19.400061
A8: Net Profit Margin (%) | B8: ='Reconstructed P&L'!B16/'Reconstructed P&L'!B5*100 -> 15.201893 | C8: ='Reconstructed P&L'!C16/'Reconstructed P&L'!C5*100 -> 11.950058 | D8: ='Reconstructed P&L'!D16/'Reconstructed P&L'!D5*100 -> 11.927974 | E8: ='Reconstructed P&L'!E16/'Reconstructed P&L'!E5*100 -> 13.589015 | F8: ='Reconstructed P&L'!F16/'Reconstructed P&L'!F5*100 -> 9.8633434 | G8: ='Reconstructed P&L'!G16/'Reconstructed P&L'!G5*100 -> 13.635063 | H8: ='Reconstructed P&L'!H16/'Reconstructed P&L'!H5*100 -> 13.281773 | I8: ='Reconstructed P&L'!I16/'Reconstructed P&L'!I5*100 -> 10.538589 | ... K8: ='Reconstructed P&L'!K16/'Reconstructed P&L'!K5*100 -> 11.335104
A9: Return on Equity / ROE (%) | B9: ='Reconstructed P&L'!B16/91293.7*100 -> 11.796652 | C9: ='Reconstructed P&L'!C16/96231.23*100 -> 9.7528214 | D9: ='Reconstructed P&L'!D16/101777.77*100 -> 10.162504 | E9: ='Reconstructed P&L'!E16/107408.17*100 -> 10.939475 | F9: ='Reconstructed P&L'!F16/113569.44*100 -> 8.9045169 | G9: ='Reconstructed P&L'!G16/118985.49*100 -> 11.572436 | H9: ='Reconstructed P&L'!H16/128667.52*100 -> 12.654312 | I9: ='Reconstructed P&L'!I16/138889.88*100 -> 12.381557 | J9: ='Reconstructed P&L'!J16/149885.02*100 -> 12.062173 | K9: ='Reconstructed P&L'!K16/161640.55*100 -> 12.156238
A10: Return on Capital Employed / ROCE (%) | B10: ='Reconstructed P&L'!B9/176390.65*100 -> 7.2151387 | C10: ='Reconstructed P&L'!C9/193570.51*100 -> 8.0732184 | D10: ='Reconstructed P&L'!D9/210475.37*100 -> 8.4709722 | E10: ='Reconstructed P&L'!E9/227106.25*100 -> 5.1411135 | F10: ='Reconstructed P&L'!F9/260108.14*100 -> 8.9573168 | G10: ='Reconstructed P&L'!G9/270215.11*100 -> 7.464775 | H10: ='Reconstructed P&L'!H9/288789.69*100 -> 8.7888144 | I10: ='Reconstructed P&L'!I9/295205.57*100 -> 9.9932362 | J10: ='Reconstructed P&L'!J9/296044.089999999*100 -> 10.267852 | K10: ='Reconstructed P&L'!K9/306006.11*100 -> 10.989983
A11: 2. LIQUIDITY RATIOS
A12: Current Ratio (times) | B12: =29756.45/31758.74 -> 0.9369531 | C12: =28399.9/36177.32 -> 0.78501945 | D12: =36731.25/42554.76 -> 0.86315256 | E12: =42133.74/55354 -> 0.76116884 | F12: =48504.86/54704.16 -> 0.88667589 | G12: =47543.21/58049.71 -> 0.81900857 | H12: =51218.48/67923.11 -> 0.75406559 | I12: =65933.05/74735.14 -> 0.88222287 | J12: =72473.33/80632.17 -> 0.89881408 | K12: =76306.79/81701.46 -> 0.93397095
A13: Quick Ratio / Acid-Test Ratio (times) | B13: =(29756.45-7010.37)/31758.74 -> 0.71621481 | C13: =(28399.9-6504.81)/36177.32 -> 0.60521592 | D13: =(36731.25-6057.38)/42554.76 -> 0.72080938 | E13: =(42133.74-7988.02)/55354 -> 0.61686093 | F13: =(48504.86-10731.86)/54704.16 -> 0.69049593 | G13: =(47543.21-9178.94)/58049.71 -> 0.66088651 | H13: =(51218.48-9691)/67923.11 -> 0.61138956 | I13: =(65933.05-13679.75)/74735.14 -> 0.6991798 | J13: =(72473.33-17369.83)/80632.17 -> 0.68339349 | K13: =(76306.79-17847.86)/81701.46 -> 0.71551879
A14: Cash Ratio (times) | B14: =(4460.78+378.72)/31758.74 -> 0.15238325 | C14: =(2930.49+0)/36177.32 -> 0.081003513 | D14: =(3978.38+0)/42554.76 -> 0.093488484 | E14: =(2144.34+0)/55354 -> 0.038738664 | F14: =(2209.11+0)/54704.16 -> 0.040382852 | G14: =(2338.46+499.99)/58049.71 -> 0.048896885 | H14: =(2747.18+0)/67923.11 -> 0.040445439 | I14: =(3741.73+50)/74735.14 -> 0.050735571 | J14: =(4600.5+50)/80632.17 -> 0.057675491 | K14: =(4778.57+50)/81701.46 -> 0.059100168
A15: 3. SOLVENCY RATIOS
A16: Debt-to-Equity Ratio (times) | B16: =86396.45/91293.7 -> 0.9463572 | C16: =100339.84/96231.23 -> 1.0426952 | D16: =115197.92/101777.77 -> 1.1318574 | E16: =135074.17/107408.17 -> 1.2575782 | F16: =160588.06/113569.44 -> 1.4140077 | G16: =174488.61/118985.49 -> 1.4664697 | H16: =184594.6/128667.52 -> 1.4346635 | I16: =186284.84/138889.88 -> 1.3412413 | J16: =185218.62/149885.02 -> 1.235738 | K16: =185243.57/161640.55 -> 1.1460217
A17: Debt Ratio (%) | B17: =86396.45/215138.32*100 -> 40.158559 | C17: =100339.84/236577.49*100 -> 42.413097 | D17: =115197.92/267832.09*100 -> 43.011246 | E17: =135074.17/290750.96*100 -> 46.456999 | F17: =160588.06/327667.45*100 -> 49.009464 | G17: =174488.61/343176.92*100 -> 50.845089 | H17: =184594.6/371140.44*100 -> 49.737129 | I17: =186284.84/383674.45*100 -> 48.55284 | J17: =185218.62/393294.53*100 -> 47.094126 | K17: =185243.57/407917.66*100 -> 45.412001
A18: Equity Ratio (%) | B18: =91293.7/215138.32*100 -> 42.434886 | C18: =96231.23/236577.49*100 -> 40.67641 | D18: =101777.77/267832.09*100 -> 38.000588 | E18: =107408.17/290750.96*100 -> 36.941639 | F18: =113569.44/327667.45*100 -> 34.65997 | G18: =118985.49/343176.92*100 -> 34.671763 | H18: =128667.52/371140.44*100 -> 34.668149 | I18: =138889.88/383674.45*100 -> 36.199929 | J18: =149885.02/393294.53*100 -> 38.110121 | K18: =161640.55/407917.66*100 -> 39.625779
A19: Interest Coverage Ratio (times) | B19: ='Reconstructed P&L'!B9/3296.41 -> 3.8608153 | C19: ='Reconstructed P&L'!C9/3597.2 -> 4.344315 | D19: ='Reconstructed P&L'!D9/3984.25 -> 4.4749476 | E19: ='Reconstructed P&L'!E9/4716.74 -> 2.475394 | F19: ='Reconstructed P&L'!F9/6781.97 -> 3.4353897 | G19: ='Reconstructed P&L'!G9/7459.03 -> 2.7042323 | H19: ='Reconstructed P&L'!H9/8216.54 -> 3.0890363 | I19: ='Reconstructed P&L'!I9/9979.23 -> 2.956199 | J19: ='Reconstructed P&L'!J9/10250.82 -> 2.9653598 | K19: ='Reconstructed P&L'!K9/11057.04 -> 3.041503
A20: 4. EFFICIENCY / ACTIVITY RATIOS
A21: Inventory Turnover (times) | B21: =43798.59/7010.37 -> 6.2476859 | C21: =47572.19/AVERAGE(' Balance Sheet'!B28,' Balance Sheet'!C28) -> 7.039816 | D21: =49628.98/AVERAGE(' Balance Sheet'!C28,' Balance Sheet'!D28) -> 7.9013261 | E21: =55207.42/AVERAGE(' Balance Sheet'!D28,' Balance Sheet'!E28) -> 7.8612813 | F21: =57018.26/AVERAGE(' Balance Sheet'!E28,' Balance Sheet'!F28) -> 6.0917335 | G21: =55880.89/AVERAGE(' Balance Sheet'!F28,' Balance Sheet'!G28) -> 5.6131235 | H21: =70020.29/AVERAGE(' Balance Sheet'!G28,' Balance Sheet'!H28) -> 7.421358 | I21: =100507.76/AVERAGE(' Balance Sheet'!H28,' Balance Sheet'!I28) -> 8.6011583 | J21: =97919.15/AVERAGE(' Balance Sheet'!I28,' Balance Sheet'!J28) -> 6.3072769 | K21: =100827.94/AVERAGE(' Balance Sheet'!J28,' Balance Sheet'!K28) -> 5.7259826
A22: Receivables Turnover (times) | B22: ='Reconstructed P&L'!B5/7732.22 -> 9.1621565 | C22: ='Reconstructed P&L'!C5/AVERAGE(' Balance Sheet'!B29,' Balance Sheet'!C29) -> 9.8975006 | D22: ='Reconstructed P&L'!D5/AVERAGE(' Balance Sheet'!C29,' Balance Sheet'!D29) -> 11.035143 | E22: ='Reconstructed P&L'!E5/AVERAGE(' Balance Sheet'!D29,' Balance Sheet'!E29) -> 10.800276 | F22: ='Reconstructed P&L'!F5/AVERAGE(' Balance Sheet'!E29,' Balance Sheet'!F29) -> 8.5266761 | G22: ='Reconstructed P&L'!G5/AVERAGE(' Balance Sheet'!F29,' Balance Sheet'!G29) -> 5.2336002 | H22: ='Reconstructed P&L'!H5/AVERAGE(' Balance Sheet'!G29,' Balance Sheet'!H29) -> 5.1374455 | I22: ='Reconstructed P&L'!I5/AVERAGE(' Balance Sheet'!H29,' Balance Sheet'!I29) -> 6.4273827 | J22: ='Reconstructed P&L'!J5/AVERAGE(' Balance Sheet'!I29,' Balance Sheet'!J29) -> 6.1129613 | K22: ='Reconstructed P&L'!K5/AVERAGE(' Balance Sheet'!J29,' Balance Sheet'!K29) -> 6.1820151
A23: Receivables Collection Period (days) | B23: =365/B22 -> 39.837783 | C23: =365/C22 -> 36.877997 | D23: =365/D22 -> 33.076145 | E23: =365/E22 -> 33.795433 | F23: =365/F22 -> 42.806833 | G23: =365/G22 -> 69.741667 | H23: =365/H22 -> 71.046982 | I23: =365/I22 -> 56.788279 | ... K23: =365/K22 -> 59.042237
A24: Payables Turnover (times) | B24: =43798.59/5311.64 -> 8.2457753 | C24: =47572.19/AVERAGE(' Balance Sheet'!B15,' Balance Sheet'!C15) -> 9.339124 | D24: =49628.98/AVERAGE(' Balance Sheet'!C15,' Balance Sheet'!D15) -> 9.4813845 | E24: =55207.42/AVERAGE(' Balance Sheet'!D15,' Balance Sheet'!E15) -> 8.4006671 | F24: =57018.26/AVERAGE(' Balance Sheet'!E15,' Balance Sheet'!F15) -> 6.8897706 | G24: =55880.89/AVERAGE(' Balance Sheet'!F15,' Balance Sheet'!G15) -> 6.9060798 | H24: =70020.29/AVERAGE(' Balance Sheet'!G15,' Balance Sheet'!H15) -> 8.2781859 | I24: =100507.76/AVERAGE(' Balance Sheet'!H15,' Balance Sheet'!I15) -> 10.39783 | J24: =97919.15/AVERAGE(' Balance Sheet'!I15,' Balance Sheet'!J15) -> 10.267958 | K24: =100827.94/AVERAGE(' Balance Sheet'!J15,' Balance Sheet'!K15) -> 10.590419
A25: Payables Payment Period (days) | B25: =365/B24 -> 44.265092 | C25: =365/C24 -> 39.082895 | D25: =365/D24 -> 38.496487 | E25: =365/E24 -> 43.44893 | F25: =365/F24 -> 52.977091 | G25: =365/G24 -> 52.851981 | H25: =365/H24 -> 44.091786 | I25: =365/I24 -> 35.10348 | ... K25: =365/K24 -> 34.465113
A26: Fixed Asset Turnover (times) | B26: ='Reconstructed P&L'!B5/91773.25 -> 0.771944 | C26: ='Reconstructed P&L'!C5/99355.72 -> 0.79046642 | D26: ='Reconstructed P&L'!D5/119759.17 -> 0.72406606 | E26: ='Reconstructed P&L'!E5/125620.62 -> 0.68831128 | F26: ='Reconstructed P&L'!F5/156811.3 -> 0.65383828 | G26: ='Reconstructed P&L'!G5/164448.86 -> 0.61408823 | H26: ='Reconstructed P&L'!H5/195570.54 -> 0.62682744 | I26: ='Reconstructed P&L'!I5/196895.88 -> 0.82875619 | J26: ='Reconstructed P&L'!J5/211751.12 -> 0.77044787 | K26: ='Reconstructed P&L'!K5/211348.91 -> 0.82020802
A27: Total Asset Turnover (times) | B27: ='Reconstructed P&L'!B5/215138.32 -> 0.32929424 | C27: ='Reconstructed P&L'!C5/236577.49 -> 0.33197309 | D27: ='Reconstructed P&L'!D5/267832.09 -> 0.32376087 | E27: ='Reconstructed P&L'!E5/290750.96 -> 0.29738884 | F27: ='Reconstructed P&L'!F5/327667.45 -> 0.31290636 | G27: ='Reconstructed P&L'!G5/343176.92 -> 0.29426836 | H27: ='Reconstructed P&L'!H5/371140.44 -> 0.33030348 | I27: ='Reconstructed P&L'!I5/383674.45 -> 0.42530505 | J27: ='Reconstructed P&L'!J5/393294.53 -> 0.41481177 | K27: ='Reconstructed P&L'!K5/407917.66 -> 0.42496339
A28: Working Capital Turnover (times) | B28: ='Reconstructed P&L'!B5/-2002.29 -> -35.381393 | C28: ='Reconstructed P&L'!C5/-7777.41999999999 -> -10.098125 | D28: ='Reconstructed P&L'!D5/-5823.51 -> -14.890255 | E28: ='Reconstructed P&L'!E5/-13220.26 -> -6.5404228 | F28: ='Reconstructed P&L'!F5/-6199.3 -> -16.53884 | G28: ='Reconstructed P&L'!G5/-10506.5 -> -9.6117746 | H28: ='Reconstructed P&L'!H5/-16704.6299999999 -> -7.3386229 | I28: ='Reconstructed P&L'!I5/-8802.08999999999 -> -18.538629 | J28: ='Reconstructed P&L'!J5/-8158.83999999999 -> -19.995882 | K28: ='Reconstructed P&L'!K5/-5394.67000000001 -> -32.133582
A29: 5. Valuation Ratio (current year)
A30: P/E Ratio (times) | B30: 11.44 | C30: Dividend yield ratio | D30: 2.72
A31: Dividend payout ratio | B31: 31.44 | C31: Price to book ratio(times) | D31: 1.53
A33: NOTES
A34: 1. As of 8 September 2026, 12:23 PM IST, NTPC was trading at approximately ₹330.30/share. For the calculations, the latest TTM EPS is ₹28.63, with TTM EPS growth of about 15.87%. The latest book value per share reported is around ₹216, and NTPC's FY2025–26 total dividend is ₹9/share
A35: 2.latest TTM EPS is ₹28.63
A36: 3.The latest book value per share reported is around ₹216
A38: 4.NTPC's FY2025–26 total dividend is ₹9/share
